.gitignore
LICENSE
MANIFEST.in
README.md
requirements.txt
setup.py
uncertainty.png
.github/workflows/build.yml
uaml/__init__.py
uaml/multiclass.py
uaml/process.py
uaml/utils.py
uaml/version.txt
uaml.egg-info/PKG-INFO
uaml.egg-info/SOURCES.txt
uaml.egg-info/dependency_links.txt
uaml.egg-info/requires.txt
uaml.egg-info/top_level.txt
uaml/tests/test_uaml.py