Metadata-Version: 2.1
Name: uaml
Version: 0.0.2
Summary: Uncertainty-aware classification.
Home-page: https://github.com/tfmortie/uaml
Author: Thomas Mortier
Author-email: thomas.mortier92@gmail.com
License: MIT license
Platform: UNKNOWN
License-File: LICENSE
